{"culture":"ru","texts":{"Identity.UserAlreadyInRole":"Пользователь уже добавлен в роль.","Identity.UserNotInRole":"Пользователь не содержится в роли.","Identity.RoleNotFound":"Роль {0} не существует.","Identity.PasswordMismatch":"Неправильный пароль.","Identity.InvalidUserName":"Недопустимое имя пользователя: {0}. Имена пользователей могут содержать только буквы и цифры.","Identity.PasswordTooShort":"Пароли должны содержать не меньше {0} символов.","Identity.PropertyTooShort":"{0} не может иметь значение NULL или быть пустым.","Identity.DuplicateUserName":"Имя {0} уже используется.","Identity.UserAlreadyHasPassword":"Пароль пользователя уже задан.","Identity.PasswordRequireNonLetterOrDigit":"В пароле должен быть по крайней мере один небуквенный или нецифровой символ.","Identity.UserIdNotFound":"Не удается найти UserId.","Identity.InvalidToken":"Недопустимый маркер.","Identity.InvalidEmail":"Адрес электронной почты '{0}' является недопустимым.","Identity.UserNameNotFound":"Пользователь {0} не существует.","Identity.LockoutNotEnabled":"Блокировка не включена для этого пользователя.","Identity.PasswordRequireUpper":"В пароле должен быть по крайней мере один символ в верхнем регистре ('A'-'Z').","Identity.PasswordRequireDigit":"В пароле должна быть по крайней мере одна цифра ('0'-'9').","Identity.PasswordRequireLower":"В пароле должен быть по крайней мере один символ в нижнем регистре ('a'-'z').","Identity.DuplicateEmail":"Адрес электронной почты '{0}' уже используется.","Identity.ExternalLoginExists":"Пользователь с таким внешним именем уже существует.","Identity.DefaultError":"Произошел неизвестный сбой.","Email":"Email","EmailSecurityCodeSubject":"Секретный код","EmailSecurityCodeBody":"Ваш секретный код: {0}","Sms":"Смс","SmsSecurityCodeMessage":"Ваш секретный код: {0}"}}